[
    {
        "auction_id": 1289,
        "company_id": 543,
        "price": "65975.00 PLN",
        "winner": true
    },
    {
        "auction_id": 1291,
        "company_id": 1067,
        "price": "150000.00 PLN",
        "winner": true
    },
    {
        "auction_id": 1293,
        "company_id": 81,
        "price": "87945.00 PLN",
        "winner": true
    },
    {
        "auction_id": 1294,
        "company_id": 1068,
        "price": "150000.00 PLN",
        "winner": true
    },
    {
        "auction_id": 1295,
        "company_id": 1069,
        "price": "25800.00 PLN",
        "winner": true
    },
    {
        "auction_id": 1295,
        "company_id": 185,
        "price": "21000.00 PLN",
        "winner": false
    },
    {
        "auction_id": 1295,
        "company_id": 1070,
        "price": "27400.00 PLN",
        "winner": false
    },
    {
        "auction_id": 1295,
        "company_id": 1071,
        "price": "33810.00 PLN",
        "winner": false
    },
    {
        "auction_id": 1295,
        "company_id": 1072,
        "price": "15692.00 PLN",
        "winner": false
    },
    {
        "auction_id": 1295,
        "company_id": 1073,
        "price": "27780.00 PLN",
        "winner": false
    },
    {
        "auction_id": 1296,
        "company_id": 1041,
        "price": "14747.70 PLN",
        "winner": true
    },
    {
        "auction_id": 1297,
        "company_id": 1074,
        "price": "45847.10 PLN",
        "winner": true
    },
    {
        "auction_id": 1297,
        "company_id": 1075,
        "price": "45611.48 PLN",
        "winner": false
    },
    {
        "auction_id": 1297,
        "company_id": 1076,
        "price": "65736.65 PLN",
        "winner": false
    },
    {
        "auction_id": 1299,
        "company_id": 220,
        "price": "100000.00 PLN",
        "winner": true
    },
    {
        "auction_id": 1300,
        "company_id": 1077,
        "price": "39852.00 PLN",
        "winner": true
    },
    {
        "auction_id": 1302,
        "company_id": 220,
        "price": "252200.00 PLN",
        "winner": true
    },
    {
        "auction_id": 1303,
        "company_id": 1078,
        "price": "312909.54 PLN",
        "winner": true
    },
    {
        "auction_id": 1304,
        "company_id": 1079,
        "price": "4400.00 PLN",
        "winner": false
    },
    {
        "auction_id": 1304,
        "company_id": 1080,
        "price": "3860.40 PLN",
        "winner": false
    },
    {
        "auction_id": 1306,
        "company_id": 1081,
        "price": "475687.90 PLN",
        "winner": false
    },
    {
        "auction_id": 1308,
        "company_id": 1082,
        "price": "463000.00 PLN",
        "winner": true
    },
    {
        "auction_id": 1310,
        "company_id": 1083,
        "price": "1920.00 PLN",
        "winner": true
    },
    {
        "auction_id": 1310,
        "company_id": 150,
        "price": "1950.00 PLN",
        "winner": false
    },
    {
        "auction_id": 1311,
        "company_id": 360,
        "price": "20272.50 PLN",
        "winner": true
    },
    {
        "auction_id": 1312,
        "company_id": 297,
        "price": "100598.74 PLN",
        "winner": true
    },
    {
        "auction_id": 1312,
        "company_id": 108,
        "price": "151200.00 PLN",
        "winner": false
    },
    {
        "auction_id": 1313,
        "company_id": 365,
        "price": "1134.00 PLN",
        "winner": true
    },
    {
        "auction_id": 1313,
        "company_id": 290,
        "price": "1208.34 PLN",
        "winner": false
    },
    {
        "auction_id": 1313,
        "company_id": 937,
        "price": "8016.00 PLN",
        "winner": false
    },
    {
        "auction_id": 1313,
        "company_id": 291,
        "price": "1304.04 PLN",
        "winner": false
    },
    {
        "auction_id": 1313,
        "company_id": 226,
        "price": "1560.00 PLN",
        "winner": false
    },
    {
        "auction_id": 1313,
        "company_id": 226,
        "price": "1960.00 PLN",
        "winner": false
    },
    {
        "auction_id": 1313,
        "company_id": 226,
        "price": "1348.20 PLN",
        "winner": false
    },
    {
        "auction_id": 1313,
        "company_id": 365,
        "price": "1233.00 PLN",
        "winner": false
    },
    {
        "auction_id": 1314,
        "company_id": 1084,
        "price": "78280.00 PLN",
        "winner": true
    },
    {
        "auction_id": 1314,
        "company_id": 1085,
        "price": "91000.50 PLN",
        "winner": false
    },
    {
        "auction_id": 1314,
        "company_id": 1086,
        "price": "81711.90 PLN",
        "winner": false
    },
    {
        "auction_id": 1315,
        "company_id": 226,
        "price": "93958.00 PLN",
        "winner": true
    },
    {
        "auction_id": 1316,
        "company_id": 1087,
        "price": "120.00 PLN",
        "winner": true
    },
    {
        "auction_id": 1316,
        "company_id": 1088,
        "price": "79.00 PLN",
        "winner": false
    },
    {
        "auction_id": 1319,
        "company_id": 1089,
        "price": "4348.34 PLN",
        "winner": true
    },
    {
        "auction_id": 1320,
        "company_id": 80,
        "price": "387287.87 PLN",
        "winner": false
    },
    {
        "auction_id": 1321,
        "company_id": 1090,
        "price": "700.00 PLN",
        "winner": false
    },
    {
        "auction_id": 1321,
        "company_id": 1091,
        "price": "700.00 PLN",
        "winner": false
    },
    {
        "auction_id": 1321,
        "company_id": 1092,
        "price": "640.00 PLN",
        "winner": false
    },
    {
        "auction_id": 1322,
        "company_id": 235,
        "price": "4760.00 PLN",
        "winner": false
    },
    {
        "auction_id": 1323,
        "company_id": 1093,
        "price": "33426.44 PLN",
        "winner": true
    },
    {
        "auction_id": 1323,
        "company_id": 1093,
        "price": "33989.44 PLN",
        "winner": false
    },
    {
        "auction_id": 1324,
        "company_id": 1094,
        "price": "86530.50 PLN",
        "winner": false
    },
    {
        "auction_id": 1324,
        "company_id": 1095,
        "price": "89850.00 PLN",
        "winner": false
    },
    {
        "auction_id": 1324,
        "company_id": 1096,
        "price": "2076.47 PLN",
        "winner": false
    },
    {
        "auction_id": 1325,
        "company_id": 394,
        "price": "731.74 PLN",
        "winner": true
    },
    {
        "auction_id": 1325,
        "company_id": 1097,
        "price": "841.16 PLN",
        "winner": false
    },
    {
        "auction_id": 1326,
        "company_id": 192,
        "price": "10759.30 PLN",
        "winner": true
    },
    {
        "auction_id": 1326,
        "company_id": 999,
        "price": "37391.14 PLN",
        "winner": false
    },
    {
        "auction_id": 1327,
        "company_id": 1098,
        "price": "40.00 PLN",
        "winner": true
    },
    {
        "auction_id": 1329,
        "company_id": 1099,
        "price": "100.00 PLN",
        "winner": true
    },
    {
        "auction_id": 1330,
        "company_id": 1100,
        "price": "100.00 PLN",
        "winner": true
    },
    {
        "auction_id": 1331,
        "company_id": 365,
        "price": "1134.00 PLN",
        "winner": true
    },
    {
        "auction_id": 1331,
        "company_id": 290,
        "price": "1208.34 PLN",
        "winner": false
    },
    {
        "auction_id": 1331,
        "company_id": 937,
        "price": "8016.00 PLN",
        "winner": false
    },
    {
        "auction_id": 1331,
        "company_id": 291,
        "price": "1304.04 PLN",
        "winner": false
    },
    {
        "auction_id": 1331,
        "company_id": 226,
        "price": "1560.00 PLN",
        "winner": false
    },
    {
        "auction_id": 1331,
        "company_id": 226,
        "price": "1960.00 PLN",
        "winner": false
    },
    {
        "auction_id": 1331,
        "company_id": 226,
        "price": "1348.20 PLN",
        "winner": false
    },
    {
        "auction_id": 1331,
        "company_id": 365,
        "price": "1233.00 PLN",
        "winner": false
    },
    {
        "auction_id": 1332,
        "company_id": 1084,
        "price": "78280.00 PLN",
        "winner": true
    },
    {
        "auction_id": 1332,
        "company_id": 1085,
        "price": "91000.50 PLN",
        "winner": false
    },
    {
        "auction_id": 1332,
        "company_id": 1086,
        "price": "81711.90 PLN",
        "winner": false
    },
    {
        "auction_id": 1333,
        "company_id": 226,
        "price": "93958.00 PLN",
        "winner": true
    },
    {
        "auction_id": 1334,
        "company_id": 1087,
        "price": "120.00 PLN",
        "winner": true
    },
    {
        "auction_id": 1334,
        "company_id": 1088,
        "price": "79.00 PLN",
        "winner": false
    },
    {
        "auction_id": 1336,
        "company_id": 1090,
        "price": "700.00 PLN",
        "winner": false
    },
    {
        "auction_id": 1336,
        "company_id": 1091,
        "price": "700.00 PLN",
        "winner": false
    },
    {
        "auction_id": 1336,
        "company_id": 1092,
        "price": "640.00 PLN",
        "winner": false
    },
    {
        "auction_id": 1338,
        "company_id": 1089,
        "price": "4348.34 PLN",
        "winner": true
    },
    {
        "auction_id": 1339,
        "company_id": 80,
        "price": "387287.87 PLN",
        "winner": false
    },
    {
        "auction_id": 1340,
        "company_id": 235,
        "price": "4760.00 PLN",
        "winner": false
    },
    {
        "auction_id": 1341,
        "company_id": 1093,
        "price": "33426.44 PLN",
        "winner": true
    },
    {
        "auction_id": 1341,
        "company_id": 1093,
        "price": "33989.44 PLN",
        "winner": false
    },
    {
        "auction_id": 1342,
        "company_id": 1094,
        "price": "86530.50 PLN",
        "winner": false
    },
    {
        "auction_id": 1342,
        "company_id": 1095,
        "price": "89850.00 PLN",
        "winner": false
    },
    {
        "auction_id": 1342,
        "company_id": 1096,
        "price": "2076.47 PLN",
        "winner": false
    },
    {
        "auction_id": 1343,
        "company_id": 394,
        "price": "731.74 PLN",
        "winner": true
    },
    {
        "auction_id": 1343,
        "company_id": 1097,
        "price": "841.16 PLN",
        "winner": false
    },
    {
        "auction_id": 1344,
        "company_id": 66,
        "price": "1425.00 PLN",
        "winner": true
    },
    {
        "auction_id": 1344,
        "company_id": 901,
        "price": "1620.00 PLN",
        "winner": false
    },
    {
        "auction_id": 1344,
        "company_id": 318,
        "price": "1550.00 PLN",
        "winner": false
    },
    {
        "auction_id": 1346,
        "company_id": 1101,
        "price": "4600.00 PLN",
        "winner": true
    },
    {
        "auction_id": 1347,
        "company_id": 1102,
        "price": "28080.00 PLN",
        "winner": true
    },
    {
        "auction_id": 1348,
        "company_id": 1103,
        "price": "2800.00 PLN",
        "winner": false
    },
    {
        "auction_id": 1348,
        "company_id": 343,
        "price": "33600.00 PLN",
        "winner": false
    },
    {
        "auction_id": 1348,
        "company_id": 530,
        "price": "4420.00 PLN",
        "winner": false
    },
    {
        "auction_id": 1348,
        "company_id": 1104,
        "price": "3120.00 PLN",
        "winner": false
    },
    {
        "auction_id": 1348,
        "company_id": 1105,
        "price": "2400.00 PLN",
        "winner": false
    },
    {
        "auction_id": 1348,
        "company_id": 1106,
        "price": "1200.00 PLN",
        "winner": false
    },
    {
        "auction_id": 1348,
        "company_id": 711,
        "price": "3600.00 PLN",
        "winner": false
    },
    {
        "auction_id": 1350,
        "company_id": 360,
        "price": "20272.50 PLN",
        "winner": true
    },
    {
        "auction_id": 1351,
        "company_id": 1107,
        "price": "5680.00 PLN",
        "winner": true
    }
]